{
	"KPlugin": {
		"Authors": [
			{
				"Email": "joshua@uuinc.co",
				"Name": "UU"
			}
		],
		"Category": "Splashscreen",
		"Description": "Fallout76 Animated Splash Screen - TV Please Standby",
		"Id": "fallout76-splash",
		"License": "GPLv3",
		"Name": "fallout76-splash",
		"ServiceTypes": ["Plasma/LookAndFeel/Splash"],
		"Website": "https://github.com/joshuadoubleyou/fallout76-splash"
	},
	"Keywords": "Desktop;Workspace;Appearance;Look and Feel;Logout;Lock;Suspend;Shutdown;Hibernate;",
	"X-Plasma-MainScript": "defaults"
}
